daproli/__init__.py
daproli/manipulation.py
daproli/processing.py
daproli/transformer.py
daproli/utils.py
daproli/tests/__init__.py
daproli/tests/test_manipulation.py
daproli/tests/test_processing.py
daproli/tests/test_transformer.py
daproli-0.22.dist-info/LICENSE
daproli-0.22.dist-info/METADATA
daproli-0.22.dist-info/WHEEL
daproli-0.22.dist-info/top_level.txt
daproli-0.22.dist-info/RECORD
