Metadata-Version: 2.1
Name: daproli
Version: 0.22
Summary: daproli is a small data processing library that attempts to make data transformation more declarative.
Home-page: https://github.com/ermshaua/daproli
Author: Arik Ermshaus
License: BSD 3-Clause License
Platform: UNKNOWN
Requires-Dist: numpy
Requires-Dist: joblib
Requires-Dist: tqdm
Requires-Dist: setuptools
